{
  "entrypoints": [
    "main"
  ],
  "origins": {
    "34": [
      85,
      261,
      514,
      532,
      608,
      918,
      979,
      34
    ],
    "261": [
      34,
      85,
      514,
      532,
      608,
      979,
      261
    ],
    "608": [
      34,
      261,
      532,
      608
    ],
    "979": [
      34,
      85,
      261,
      514,
      532,
      979
    ],
    "17896441": [
      34,
      532,
      918
    ],
    "main": [
      303,
      532,
      179
    ],
    "runtime~main": [
      179,
      532,
      303
    ],
    "06e21769": [
      326
    ],
    "0e384e19": [
      671
    ],
    "193cb657": [
      966
    ],
    "1be78505": [
      34,
      261,
      532,
      979,
      608
    ],
    "1c5fc5c8": [
      62
    ],
    "1c76e469": [
      521
    ],
    "1f391b9e": [
      34,
      261,
      532,
      979,
      85
    ],
    "20b0836f": [
      870
    ],
    "275b4906": [
      830
    ],
    "2bd40aca": [
      527
    ],
    "2c397297": [
      631
    ],
    "3b71412b": [
      398
    ],
    "3daa37df": [
      763
    ],
    "3fa7bede": [
      305
    ],
    "41fe007c": [
      425
    ],
    "5c208b63": [
      380
    ],
    "5ee1360a": [
      536
    ],
    "5fafcaa2": [
      619
    ],
    "7a1375f1": [
      91
    ],
    "935f2afb": [
      53
    ],
    "a2a03e9f": [
      978
    ],
    "a422ab59": [
      571
    ],
    "b3618e0d": [
      331
    ],
    "b6c95e34": [
      723
    ],
    "c1090143": [
      864
    ],
    "c59e713d": [
      684
    ],
    "cd056220": [
      628
    ],
    "e108989d": [
      661
    ],
    "e898175c": [
      236
    ],
    "f6aa51b3": [
      652
    ],
    "fb87d503": [
      531
    ],
    "styles": [
      34,
      85,
      179,
      261,
      303,
      514,
      608,
      918,
      979,
      532
    ]
  },
  "assets": {
    "34": {
      "js": [
        {
          "file": "assets/js/34.427ee85f.js",
          "hash": "9ce121fd39fab27ed0dd",
          "publicPath": "/assets/js/34.427ee85f.js"
        }
      ]
    },
    "53": {
      "js": [
        {
          "file": "assets/js/935f2afb.fc57a79f.js",
          "hash": "2684799c9d7f468e6c1b",
          "publicPath": "/assets/js/935f2afb.fc57a79f.js"
        }
      ]
    },
    "62": {
      "js": [
        {
          "file": "assets/js/1c5fc5c8.45fe924a.js",
          "hash": "247f7f216ca83162f224",
          "publicPath": "/assets/js/1c5fc5c8.45fe924a.js"
        }
      ]
    },
    "85": {
      "js": [
        {
          "file": "assets/js/1f391b9e.7afc1529.js",
          "hash": "9e03b232b1b2a4ae0920",
          "publicPath": "/assets/js/1f391b9e.7afc1529.js"
        }
      ]
    },
    "91": {
      "js": [
        {
          "file": "assets/js/7a1375f1.b5e0ac26.js",
          "hash": "604fdd79527e47baf477",
          "publicPath": "/assets/js/7a1375f1.b5e0ac26.js"
        }
      ]
    },
    "179": {
      "js": [
        {
          "file": "assets/js/main.f898ffe9.js",
          "hash": "60765514d625a6f9dcad",
          "publicPath": "/assets/js/main.f898ffe9.js"
        }
      ]
    },
    "236": {
      "js": [
        {
          "file": "assets/js/e898175c.010d4216.js",
          "hash": "647d58baeaf8442bc6ef",
          "publicPath": "/assets/js/e898175c.010d4216.js"
        }
      ]
    },
    "261": {
      "js": [
        {
          "file": "assets/js/261.3205df4e.js",
          "hash": "a5dc2b6a69ac982451d7",
          "publicPath": "/assets/js/261.3205df4e.js"
        }
      ]
    },
    "303": {
      "js": [
        {
          "file": "assets/js/runtime~main.3a509436.js",
          "hash": "247cc2f8cbafe79e727b",
          "publicPath": "/assets/js/runtime~main.3a509436.js"
        }
      ]
    },
    "305": {
      "js": [
        {
          "file": "assets/js/3fa7bede.2fffd80a.js",
          "hash": "79c1fe1fbc5f1235a3fb",
          "publicPath": "/assets/js/3fa7bede.2fffd80a.js"
        }
      ]
    },
    "326": {
      "js": [
        {
          "file": "assets/js/06e21769.5b4088e0.js",
          "hash": "468494f1697b2cec17a7",
          "publicPath": "/assets/js/06e21769.5b4088e0.js"
        }
      ]
    },
    "331": {
      "js": [
        {
          "file": "assets/js/b3618e0d.d34be8db.js",
          "hash": "f334a4f13160131b3baa",
          "publicPath": "/assets/js/b3618e0d.d34be8db.js"
        }
      ]
    },
    "380": {
      "js": [
        {
          "file": "assets/js/5c208b63.f1d91504.js",
          "hash": "2f3002af289b04c38c40",
          "publicPath": "/assets/js/5c208b63.f1d91504.js"
        }
      ]
    },
    "398": {
      "js": [
        {
          "file": "assets/js/3b71412b.7147cb06.js",
          "hash": "19335fce145bc6579291",
          "publicPath": "/assets/js/3b71412b.7147cb06.js"
        }
      ]
    },
    "425": {
      "js": [
        {
          "file": "assets/js/41fe007c.fb2da587.js",
          "hash": "c0cda4c0c886ccdb2a2d",
          "publicPath": "/assets/js/41fe007c.fb2da587.js"
        }
      ]
    },
    "521": {
      "js": [
        {
          "file": "assets/js/1c76e469.5abe497e.js",
          "hash": "ec2e00d685fe1da70aed",
          "publicPath": "/assets/js/1c76e469.5abe497e.js"
        }
      ]
    },
    "527": {
      "js": [
        {
          "file": "assets/js/2bd40aca.ae2b1b59.js",
          "hash": "d7443334eb6240c906a3",
          "publicPath": "/assets/js/2bd40aca.ae2b1b59.js"
        }
      ]
    },
    "531": {
      "js": [
        {
          "file": "assets/js/fb87d503.3fbbb071.js",
          "hash": "1bf4c2de3f72bb27888a",
          "publicPath": "/assets/js/fb87d503.3fbbb071.js"
        }
      ]
    },
    "532": {
      "css": [
        {
          "file": "assets/css/styles.99ffe202.css",
          "hash": "92830f2f5666c338e232",
          "publicPath": "/assets/css/styles.99ffe202.css"
        }
      ]
    },
    "536": {
      "js": [
        {
          "file": "assets/js/5ee1360a.b0d5bd27.js",
          "hash": "e7814d336c644158fd64",
          "publicPath": "/assets/js/5ee1360a.b0d5bd27.js"
        }
      ]
    },
    "571": {
      "js": [
        {
          "file": "assets/js/a422ab59.7a59af49.js",
          "hash": "9ecec70463744a4c73e3",
          "publicPath": "/assets/js/a422ab59.7a59af49.js"
        }
      ]
    },
    "608": {
      "js": [
        {
          "file": "assets/js/608.6bb021ab.js",
          "hash": "409c676a06a04ed85647",
          "publicPath": "/assets/js/608.6bb021ab.js"
        },
        {
          "file": "assets/js/1be78505.bc964206.js",
          "hash": "92475d8298338bfc2c29",
          "publicPath": "/assets/js/1be78505.bc964206.js"
        }
      ]
    },
    "619": {
      "js": [
        {
          "file": "assets/js/5fafcaa2.94886454.js",
          "hash": "6ac508cfcc37377e2027",
          "publicPath": "/assets/js/5fafcaa2.94886454.js"
        }
      ]
    },
    "628": {
      "js": [
        {
          "file": "assets/js/cd056220.2149da60.js",
          "hash": "28769be62cf91868914d",
          "publicPath": "/assets/js/cd056220.2149da60.js"
        }
      ]
    },
    "631": {
      "js": [
        {
          "file": "assets/js/2c397297.77e1bde3.js",
          "hash": "41fc513b256eff4c59ec",
          "publicPath": "/assets/js/2c397297.77e1bde3.js"
        }
      ]
    },
    "652": {
      "js": [
        {
          "file": "assets/js/f6aa51b3.020474c2.js",
          "hash": "dbbb46d0a5a4a438342e",
          "publicPath": "/assets/js/f6aa51b3.020474c2.js"
        }
      ]
    },
    "661": {
      "js": [
        {
          "file": "assets/js/e108989d.717d92fa.js",
          "hash": "90d9ad6eebd289babeab",
          "publicPath": "/assets/js/e108989d.717d92fa.js"
        }
      ]
    },
    "671": {
      "js": [
        {
          "file": "assets/js/0e384e19.aa43e77c.js",
          "hash": "275a95e7389665601f58",
          "publicPath": "/assets/js/0e384e19.aa43e77c.js"
        }
      ]
    },
    "684": {
      "js": [
        {
          "file": "assets/js/c59e713d.efa0ddc3.js",
          "hash": "a2c0d5630c907dea1bed",
          "publicPath": "/assets/js/c59e713d.efa0ddc3.js"
        }
      ]
    },
    "723": {
      "js": [
        {
          "file": "assets/js/b6c95e34.a7edd8fe.js",
          "hash": "5c30e48634e8c463afa6",
          "publicPath": "/assets/js/b6c95e34.a7edd8fe.js"
        }
      ]
    },
    "763": {
      "js": [
        {
          "file": "assets/js/3daa37df.6ff69dcd.js",
          "hash": "bd9131cd8516b5630797",
          "publicPath": "/assets/js/3daa37df.6ff69dcd.js"
        }
      ]
    },
    "830": {
      "js": [
        {
          "file": "assets/js/275b4906.976a3a13.js",
          "hash": "d557009eacd56e0d8c46",
          "publicPath": "/assets/js/275b4906.976a3a13.js"
        }
      ]
    },
    "864": {
      "js": [
        {
          "file": "assets/js/c1090143.aeb88a05.js",
          "hash": "3643eb75268d839ff096",
          "publicPath": "/assets/js/c1090143.aeb88a05.js"
        }
      ]
    },
    "870": {
      "js": [
        {
          "file": "assets/js/20b0836f.afd3a9d2.js",
          "hash": "3c1494c726eb41ea356a",
          "publicPath": "/assets/js/20b0836f.afd3a9d2.js"
        }
      ]
    },
    "918": {
      "js": [
        {
          "file": "assets/js/17896441.30d0e090.js",
          "hash": "cddbd605fb1985f2560b",
          "publicPath": "/assets/js/17896441.30d0e090.js"
        }
      ]
    },
    "966": {
      "js": [
        {
          "file": "assets/js/193cb657.250fa7cd.js",
          "hash": "5df5d4cd75c1edb2e47a",
          "publicPath": "/assets/js/193cb657.250fa7cd.js"
        }
      ]
    },
    "978": {
      "js": [
        {
          "file": "assets/js/a2a03e9f.d562c5a0.js",
          "hash": "6b7cd22b7c5df190043b",
          "publicPath": "/assets/js/a2a03e9f.d562c5a0.js"
        }
      ]
    },
    "979": {
      "js": [
        {
          "file": "assets/js/979.baf8f029.js",
          "hash": "fd5ab610ae00af184efa",
          "publicPath": "/assets/js/979.baf8f029.js"
        }
      ]
    }
  }
}